MANIFEST.in
README.md
license
setup.cfg
setup.py
test_settings.py
tox.ini
django_natural_duration.egg-info/PKG-INFO
django_natural_duration.egg-info/SOURCES.txt
django_natural_duration.egg-info/dependency_links.txt
django_natural_duration.egg-info/requires.txt
django_natural_duration.egg-info/top_level.txt
natural_duration/__init__.py
natural_duration/apps.py
natural_duration/fields.py
natural_duration/tests.py