Metadata-Version: 1.1
Name: django-natural-duration
Version: 0.1
Summary: A human-readable duration form field for Django
Home-page: https://github.com/jmerdich/django-natural-duration/
Author: jmerdich
Author-email: jake@merdich.com
License: New BSD
Download-URL: https://github.com/jmerdich/django-natural-duration/tarball/0.1
Keywords: forms,timedelta,humanize
Platform: UNKNOWN
Classifier: Environment :: Web Environment
Classifier: Framework :: Django
Classifier: Framework :: Django :: 1.8
Classifier: Intended Audience :: Developers
Classifier: License :: OSI Approved :: BSD License
Classifier: Operating System :: OS Independent
Classifier: Programming Language :: Python
Classifier: Programming Language :: Python :: 2
Classifier: Programming Language :: Python :: 2.7
Classifier: Programming Language :: Python :: 3
Classifier: Programming Language :: Python :: 3.4
Classifier: Topic :: Internet :: WWW/HTTP
Classifier: Topic :: Internet :: WWW/HTTP :: Dynamic Content
